dsf_ez_tools/README.md
dsf_ez_tools/__init__.py
dsf_ez_tools/ez_captcha_recognize.pyd
dsf_ez_tools/ez_captcha_recognize.pyi
dsf_ez_tools/ez_curl_cffi.pyd
dsf_ez_tools/ez_curl_cffi.pyi
dsf_ez_tools/ez_decorator.pyd
dsf_ez_tools/ez_decorator.pyi
dsf_ez_tools/ez_dingwarn.pyd
dsf_ez_tools/ez_dingwarn.pyi
dsf_ez_tools/ez_exec_js.pyd
dsf_ez_tools/ez_exec_js.pyi
dsf_ez_tools/ez_kafka.pyd
dsf_ez_tools/ez_kafka.pyi
dsf_ez_tools/ez_logging.pyd
dsf_ez_tools/ez_logging.pyi
dsf_ez_tools/ez_requests.pyd
dsf_ez_tools/ez_requests.pyi
dsf_ez_tools/ez_rocketmq.pyd
dsf_ez_tools/ez_rocketmq.pyi
dsf_ez_tools/ez_tls_client.pyd
dsf_ez_tools/ez_tls_client.pyi
dsf_ez_tools/ez_zmq.pyd
dsf_ez_tools/ez_zmq.pyi
dsf_ez_tools/ezselenium.pyd
dsf_ez_tools/ezselenium.pyi
dsf_ez_tools/m3u8downloader.pyd
dsf_ez_tools/m3u8downloader.pyi
dsf_ez_tools/requirements.txt
dsf_ez_tools/ez_crypto/__init__.py
dsf_ez_tools/ez_crypto/base.pyd
dsf_ez_tools/ez_crypto/base.pyi
dsf_ez_tools/ez_crypto/ez_aes.pyd
dsf_ez_tools/ez_crypto/ez_aes.pyi
dsf_ez_tools/ez_crypto/ez_base64.pyd
dsf_ez_tools/ez_crypto/ez_base64.pyi
dsf_ez_tools/ez_crypto/ez_convert_base.pyd
dsf_ez_tools/ez_crypto/ez_convert_base.pyi
dsf_ez_tools/ez_crypto/ez_convert_datatype.pyd
dsf_ez_tools/ez_crypto/ez_convert_datatype.pyi
dsf_ez_tools/ez_crypto/ez_des.pyd
dsf_ez_tools/ez_crypto/ez_des.pyi
dsf_ez_tools/ez_crypto/ez_hex.pyd
dsf_ez_tools/ez_crypto/ez_hex.pyi
dsf_ez_tools/ez_crypto/ez_md5.pyd
dsf_ez_tools/ez_crypto/ez_md5.pyi
dsf_ez_tools/ez_crypto/ez_rsa.pyd
dsf_ez_tools/ez_crypto/ez_rsa.pyi
dsf_ez_tools/ez_crypto/ez_sha.pyd
dsf_ez_tools/ez_crypto/ez_sha.pyi
dsf_ez_tools/ez_db/__init__.py
dsf_ez_tools/ez_db/ez_async_mysql.pyd
dsf_ez_tools/ez_db/ez_async_mysql.pyi
dsf_ez_tools/ez_db/ez_mysql_migrate.pyd
dsf_ez_tools/ez_db/ez_mysql_migrate.pyi
dsf_ez_tools/ez_db/ez_mysql_pool.pyd
dsf_ez_tools/ez_db/ez_mysql_pool.pyi
dsf_ez_tools/ez_db/ez_pymongo.pyd
dsf_ez_tools/ez_db/ez_pymongo.pyi
dsf_ez_tools/ez_db/ez_pymysql.pyd
dsf_ez_tools/ez_db/ez_pymysql.pyi
dsf_ez_tools-0.0.8.dist-info/METADATA
dsf_ez_tools-0.0.8.dist-info/WHEEL
dsf_ez_tools-0.0.8.dist-info/pbr.json
dsf_ez_tools-0.0.8.dist-info/top_level.txt
dsf_ez_tools-0.0.8.dist-info/RECORD
